pyTorchAutoForge/__init__.py
pyTorchAutoForge/api/__init__.py
pyTorchAutoForge/api/matlab/CTorchModelWrapper.m
pyTorchAutoForge/api/matlab/EnumTorchWrapperMode.m
pyTorchAutoForge/api/matlab/TorchModelMATLABwrapper.py
pyTorchAutoForge/api/matlab/__init__.py
pyTorchAutoForge/api/mlflow/__init__.py
pyTorchAutoForge/api/mlflow/mlflow_api.py
pyTorchAutoForge/api/onnx/ModelHandlerONNx.py
pyTorchAutoForge/api/onnx/__init__.py
pyTorchAutoForge/api/tcp/__init__.py
pyTorchAutoForge/api/tcp/tcpServerPy.py
pyTorchAutoForge/api/tcp/tcp_socket_server.py
pyTorchAutoForge/api/tcp/tcp_torchModel_eval.py
pyTorchAutoForge/api/tcp/.deprecated/torchModelOverTCP_legacy.py
pyTorchAutoForge/api/telegram/AutoForge_AlertSystem_bot.py.wip
pyTorchAutoForge/api/telegram/__init__.py
pyTorchAutoForge/api/telegram/bot_token_private.json
pyTorchAutoForge/api/tensorrt/.gitkeep
pyTorchAutoForge/api/tensorrt/TODO
pyTorchAutoForge/api/tensorrt/TRTengineExporter.py
pyTorchAutoForge/api/tensorrt/__init__.py
pyTorchAutoForge/api/torch/__init__.py
pyTorchAutoForge/api/torch/torchModulesIO.py
pyTorchAutoForge/datasets/.experimental.py
pyTorchAutoForge/datasets/DataAugmentation.py
pyTorchAutoForge/datasets/DataloaderIndex.py
pyTorchAutoForge/datasets/DatasetClasses.py
pyTorchAutoForge/datasets/ImagesAugmentation.py
pyTorchAutoForge/datasets/LabelsClasses.py
pyTorchAutoForge/datasets/__init__.py
pyTorchAutoForge/datasets/auxiliary_functions.py
pyTorchAutoForge/datasets/noise_models/FrameCameraNoiseModels.py
pyTorchAutoForge/datasets/noise_models/__init__.py
pyTorchAutoForge/evaluation/ModelEvaluator.py
pyTorchAutoForge/evaluation/ModelExplainer.py
pyTorchAutoForge/evaluation/ModelProfiler.py
pyTorchAutoForge/evaluation/ResultsPlotter.py
pyTorchAutoForge/evaluation/__init__.py
pyTorchAutoForge/extra/data_analysis_tools_module.py
pyTorchAutoForge/extra/experimental_pysr_module.py
pyTorchAutoForge/extra/xgboost_regression_module.py
pyTorchAutoForge/hparams_optim/ModelHparamsOptimizer.py
pytorchautoforge-0.2.1.dist-info/METADATA
pytorchautoforge-0.2.1.dist-info/WHEEL
pytorchautoforge-0.2.1.dist-info/licenses/LICENSE
pytorchautoforge-0.2.1.dist-info/RECORD
